{
  "version": "4.5.6",
  "flags": {},
  "shapes": [
    {
      "label": "rubber",
      "points": [
        [
          818,
          667
        ],
        [
          816,
          669
        ],
        [
          819,
          673
        ],
        [
          820,
          681
        ],
        [
          820,
          691
        ],
        [
          818,
          693
        ],
        [
          818,
          697
        ],
        [
          819,
          701
        ],
        [
          822,
          706
        ],
        [
          822,
          708
        ],
        [
          822,
          713
        ],
        [
          822,
          715
        ],
        [
          821,
          720
        ],
        [
          823,
          723
        ],
        [
          823,
          725
        ],
        [
          822,
          726
        ],
        [
          822,
          728
        ],
        [
          823,
          729
        ],
        [
          823,
          732
        ],
        [
          821,
          737
        ],
        [
          821,
          745
        ],
        [
          823,
          752
        ],
        [
          824,
          752
        ],
        [
          825,
          753
        ],
        [
          826,
          755
        ],
        [
          826,
          760
        ],
        [
          825,
          761
        ],
        [
          825,
          765
        ],
        [
          827,
          768
        ],
        [
          827,
          771
        ],
        [
          830,
          774
        ],
        [
          831,
          777
        ],
        [
          840,
          786
        ],
        [
          843,
          791
        ],
        [
          844,
          793
        ],
        [
          844,
          795
        ],
        [
          846,
          798
        ],
        [
          845,
          801
        ],
        [
          847,
          805
        ],
        [
          846,
          808
        ],
        [
          846,
          814
        ],
        [
          848,
          816
        ],
        [
          848,
          819
        ],
        [
          847,
          820
        ],
        [
          848,
          824
        ],
        [
          846,
          827
        ],
        [
          846,
          831
        ],
        [
          845,
          833
        ],
        [
          843,
          835
        ],
        [
          841,
          839
        ],
        [
          844,
          843
        ],
        [
          844,
          846
        ],
        [
          845,
          847
        ],
        [
          845,
          849
        ],
        [
          844,
          852
        ],
        [
          845,
          856
        ],
        [
          843,
          859
        ],
        [
          843,
          860
        ],
        [
          842,
          862
        ],
        [
          838,
          863
        ],
        [
          839,
          868
        ],
        [
          837,
          871
        ],
        [
          838,
          876
        ],
        [
          837,
          880
        ],
        [
          841,
          887
        ],
        [
          841,
          896
        ],
        [
          836,
          901
        ],
        [
          835,
          903
        ],
        [
          836,
          909
        ],
        [
          838,
          913
        ],
        [
          837,
          915
        ],
        [
          836,
          920
        ],
        [
          835,
          924
        ],
        [
          837,
          925
        ],
        [
          837,
          928
        ],
        [
          835,
          935
        ],
        [
          837,
          940
        ],
        [
          834,
          945
        ],
        [
          834,
          947
        ],
        [
          836,
          948
        ],
        [
          837,
          955
        ],
        [
          837,
          958
        ],
        [
          833,
          963
        ],
        [
          835,
          966
        ],
        [
          836,
          971
        ],
        [
          834,
          974
        ],
        [
          834,
          977
        ],
        [
          836,
          981
        ],
        [
          835,
          983
        ],
        [
          833,
          987
        ],
        [
          834,
          989
        ],
        [
          861,
          988
        ],
        [
          864,
          984
        ],
        [
          867,
          980
        ],
        [
          867,
          979
        ],
        [
          869,
          977
        ],
        [
          872,
          975
        ],
        [
          875,
          976
        ],
        [
          881,
          970
        ],
        [
          885,
          964
        ],
        [
          891,
          958
        ],
        [
          894,
          954
        ],
        [
          897,
          950
        ],
        [
          899,
          947
        ],
        [
          901,
          944
        ],
        [
          904,
          939
        ],
        [
          905,
          932
        ],
        [
          907,
          929
        ],
        [
          911,
          925
        ],
        [
          913,
          922
        ],
        [
          915,
          919
        ],
        [
          916,
          917
        ],
        [
          916,
          911
        ],
        [
          920,
          904
        ],
        [
          919,
          899
        ],
        [
          920,
          897
        ],
        [
          923,
          893
        ],
        [
          923,
          891
        ],
        [
          922,
          889
        ],
        [
          923,
          887
        ],
        [
          925,
          885
        ],
        [
          926,
          883
        ],
        [
          926,
          880
        ],
        [
          925,
          879
        ],
        [
          925,
          877
        ],
        [
          927,
          872
        ],
        [
          928,
          866
        ],
        [
          927,
          861
        ],
        [
          929,
          858
        ],
        [
          928,
          853
        ],
        [
          928,
          850
        ],
        [
          930,
          848
        ],
        [
          930,
          846
        ],
        [
          928,
          842
        ],
        [
          930,
          839
        ],
        [
          930,
          837
        ],
        [
          928,
          833
        ],
        [
          929,
          827
        ],
        [
          927,
          825
        ],
        [
          927,
          822
        ],
        [
          928,
          821
        ],
        [
          928,
          819
        ],
        [
          927,
          818
        ],
        [
          928,
          814
        ],
        [
          926,
          811
        ],
        [
          925,
          807
        ],
        [
          925,
          804
        ],
        [
          926,
          803
        ],
        [
          926,
          799
        ],
        [
          925,
          796
        ],
        [
          924,
          794
        ],
        [
          922,
          792
        ],
        [
          921,
          790
        ],
        [
          922,
          786
        ],
        [
          920,
          784
        ],
        [
          920,
          780
        ],
        [
          916,
          773
        ],
        [
          915,
          768
        ],
        [
          911,
          759
        ],
        [
          909,
          755
        ],
        [
          908,
          753
        ],
        [
          904,
          747
        ],
        [
          903,
          745
        ],
        [
          902,
          743
        ],
        [
          902,
          740
        ],
        [
          898,
          736
        ],
        [
          897,
          734
        ],
        [
          897,
          732
        ],
        [
          896,
          730
        ],
        [
          892,
          726
        ],
        [
          890,
          723
        ],
        [
          890,
          720
        ],
        [
          889,
          718
        ],
        [
          881,
          711
        ],
        [
          878,
          708
        ],
        [
          876,
          703
        ],
        [
          862,
          689
        ],
        [
          845,
          676
        ],
        [
          842,
          674
        ],
        [
          835,
          670
        ],
        [
          829,
          667
        ],
        [
          824,
          666
        ]
      ],
      "group_id": null,
      "shape_type": "polygon",
      "flags": {}
    },
    {
      "label": "brick",
      "points": [
        [
          712,
          370
        ],
        [
          703,
          387
        ],
        [
          692,
          406
        ],
        [
          690,
          413
        ],
        [
          687,
          420
        ],
        [
          687,
          421
        ],
        [
          686,
          423
        ],
        [
          687,
          425
        ],
        [
          686,
          427
        ],
        [
          687,
          433
        ],
        [
          681,
          443
        ],
        [
          680,
          454
        ],
        [
          679,
          457
        ],
        [
          679,
          458
        ],
        [
          678,
          460
        ],
        [
          680,
          463
        ],
        [
          682,
          464
        ],
        [
          682,
          462
        ],
        [
          686,
          462
        ],
        [
          692,
          456
        ],
        [
          696,
          458
        ],
        [
          703,
          458
        ],
        [
          705,
          456
        ],
        [
          711,
          460
        ],
        [
          712,
          459
        ],
        [
          714,
          460
        ],
        [
          716,
          460
        ],
        [
          719,
          458
        ],
        [
          724,
          462
        ],
        [
          729,
          463
        ],
        [
          733,
          463
        ],
        [
          736,
          464
        ],
        [
          741,
          464
        ],
        [
          749,
          469
        ],
        [
          748,
          471
        ],
        [
          749,
          469
        ],
        [
          751,
          468
        ],
        [
          758,
          471
        ],
        [
          762,
          468
        ],
        [
          769,
          470
        ],
        [
          771,
          474
        ],
        [
          772,
          472
        ],
        [
          774,
          470
        ],
        [
          777,
          469
        ],
        [
          779,
          469
        ],
        [
          781,
          470
        ],
        [
          783,
          470
        ],
        [
          787,
          468
        ],
        [
          789,
          470
        ],
        [
          791,
          470
        ],
        [
          795,
          470
        ],
        [
          796,
          468
        ],
        [
          797,
          467
        ],
        [
          804,
          455
        ],
        [
          805,
          451
        ],
        [
          805,
          448
        ],
        [
          806,
          445
        ],
        [
          806,
          436
        ],
        [
          807,
          430
        ],
        [
          808,
          428
        ],
        [
          809,
          425
        ],
        [
          810,
          409
        ],
        [
          809,
          404
        ],
        [
          810,
          401
        ],
        [
          811,
          398
        ],
        [
          811,
          397
        ],
        [
          812,
          395
        ],
        [
          811,
          393
        ],
        [
          811,
          390
        ],
        [
          809,
          388
        ],
        [
          807,
          382
        ],
        [
          808,
          379
        ],
        [
          806,
          376
        ],
        [
          805,
          374
        ],
        [
          803,
          372
        ],
        [
          796,
          368
        ],
        [
          789,
          366
        ],
        [
          787,
          366
        ],
        [
          780,
          367
        ],
        [
          775,
          364
        ],
        [
          770,
          366
        ],
        [
          766,
          364
        ],
        [
          764,
          364
        ],
        [
          762,
          365
        ],
        [
          760,
          365
        ],
        [
          755,
          363
        ],
        [
          753,
          363
        ],
        [
          752,
          363
        ],
        [
          751,
          364
        ],
        [
          746,
          363
        ],
        [
          743,
          362
        ],
        [
          741,
          362
        ],
        [
          739,
          363
        ],
        [
          733,
          361
        ],
        [
          730,
          361
        ],
        [
          726,
          363
        ],
        [
          722,
          361
        ],
        [
          720,
          361
        ],
        [
          717,
          362
        ],
        [
          712,
          366
        ]
      ],
      "group_id": null,
      "shape_type": "polygon",
      "flags": {}
    },
    {
      "label": "concrete",
      "points": [
        [
          485,
          441
        ],
        [
          486,
          434
        ],
        [
          489,
          429
        ],
        [
          493,
          427
        ],
        [
          495,
          423
        ],
        [
          495,
          421
        ],
        [
          496,
          420
        ],
        [
          494,
          415
        ],
        [
          495,
          413
        ],
        [
          495,
          411
        ],
        [
          496,
          409
        ],
        [
          494,
          406
        ],
        [
          495,
          403
        ],
        [
          494,
          401
        ],
        [
          495,
          397
        ],
        [
          494,
          397
        ],
        [
          495,
          389
        ],
        [
          494,
          389
        ],
        [
          494,
          385
        ],
        [
          494,
          384
        ],
        [
          493,
          382
        ],
        [
          491,
          382
        ],
        [
          489,
          383
        ],
        [
          485,
          382
        ],
        [
          479,
          376
        ],
        [
          474,
          375
        ],
        [
          472,
          374
        ],
        [
          469,
          376
        ],
        [
          463,
          373
        ],
        [
          452,
          366
        ],
        [
          450,
          366
        ],
        [
          447,
          368
        ],
        [
          440,
          364
        ],
        [
          438,
          364
        ],
        [
          437,
          365
        ],
        [
          434,
          366
        ],
        [
          432,
          364
        ],
        [
          430,
          364
        ],
        [
          427,
          366
        ],
        [
          425,
          364
        ],
        [
          422,
          364
        ],
        [
          421,
          366
        ],
        [
          419,
          367
        ],
        [
          417,
          367
        ],
        [
          415,
          368
        ],
        [
          414,
          370
        ],
        [
          411,
          370
        ],
        [
          409,
          372
        ],
        [
          407,
          376
        ],
        [
          399,
          382
        ],
        [
          397,
          382
        ],
        [
          396,
          384
        ],
        [
          391,
          384
        ],
        [
          390,
          386
        ],
        [
          388,
          386
        ],
        [
          387,
          389
        ],
        [
          384,
          389
        ],
        [
          381,
          390
        ],
        [
          380,
          392
        ],
        [
          376,
          392
        ],
        [
          375,
          393
        ],
        [
          374,
          394
        ],
        [
          371,
          397
        ],
        [
          367,
          400
        ],
        [
          365,
          404
        ],
        [
          364,
          408
        ],
        [
          363,
          411
        ],
        [
          362,
          416
        ],
        [
          362,
          418
        ],
        [
          362,
          423
        ],
        [
          360,
          428
        ],
        [
          359,
          441
        ],
        [
          359,
          445
        ],
        [
          360,
          451
        ],
        [
          361,
          458
        ],
        [
          362,
          460
        ],
        [
          366,
          464
        ],
        [
          370,
          467
        ],
        [
          371,
          465
        ],
        [
          372,
          465
        ],
        [
          375,
          462
        ],
        [
          380,
          466
        ],
        [
          383,
          469
        ],
        [
          384,
          473
        ],
        [
          384,
          474
        ],
        [
          385,
          477
        ],
        [
          386,
          480
        ],
        [
          385,
          483
        ],
        [
          386,
          485
        ],
        [
          394,
          490
        ],
        [
          397,
          490
        ],
        [
          398,
          488
        ],
        [
          400,
          488
        ],
        [
          402,
          489
        ],
        [
          404,
          489
        ],
        [
          407,
          489
        ],
        [
          411,
          486
        ],
        [
          428,
          497
        ],
        [
          428,
          500
        ],
        [
          427,
          501
        ],
        [
          429,
          503
        ],
        [
          434,
          507
        ],
        [
          436,
          507
        ],
        [
          440,
          506
        ],
        [
          441,
          504
        ],
        [
          444,
          504
        ],
        [
          446,
          502
        ],
        [
          447,
          497
        ],
        [
          468,
          463
        ],
        [
          475,
          457
        ],
        [
          483,
          446
        ]
      ],
      "group_id": null,
      "shape_type": "polygon",
      "flags": {}
    },
    {
      "label": "concrete",
      "points": [
        [
          73,
          18
        ],
        [
          66,
          19
        ],
        [
          60,
          20
        ],
        [
          57,
          21
        ],
        [
          54,
          22
        ],
        [
          52,
          24
        ],
        [
          49,
          25
        ],
        [
          47,
          28
        ],
        [
          45,
          28
        ],
        [
          44,
          30
        ],
        [
          44,
          32
        ],
        [
          42,
          34
        ],
        [
          40,
          39
        ],
        [
          38,
          39
        ],
        [
          36,
          40
        ],
        [
          33,
          44
        ],
        [
          30,
          45
        ],
        [
          30,
          54
        ],
        [
          27,
          55
        ],
        [
          25,
          55
        ],
        [
          24,
          63
        ],
        [
          27,
          70
        ],
        [
          28,
          72
        ],
        [
          34,
          74
        ],
        [
          33,
          82
        ],
        [
          35,
          82
        ],
        [
          36,
          83
        ],
        [
          40,
          84
        ],
        [
          41,
          85
        ],
        [
          42,
          93
        ],
        [
          43,
          95
        ],
        [
          46,
          97
        ],
        [
          47,
          99
        ],
        [
          51,
          101
        ],
        [
          51,
          107
        ],
        [
          52,
          109
        ],
        [
          54,
          111
        ],
        [
          54,
          113
        ],
        [
          55,
          115
        ],
        [
          59,
          116
        ],
        [
          61,
          119
        ],
        [
          64,
          120
        ],
        [
          67,
          121
        ],
        [
          75,
          121
        ],
        [
          77,
          123
        ],
        [
          80,
          124
        ],
        [
          84,
          125
        ],
        [
          87,
          124
        ],
        [
          89,
          123
        ],
        [
          91,
          122
        ],
        [
          92,
          121
        ],
        [
          95,
          117
        ],
        [
          96,
          115
        ],
        [
          96,
          112
        ],
        [
          98,
          109
        ],
        [
          98,
          106
        ],
        [
          100,
          103
        ],
        [
          100,
          96
        ],
        [
          102,
          91
        ],
        [
          104,
          90
        ],
        [
          104,
          83
        ],
        [
          105,
          77
        ],
        [
          107,
          74
        ],
        [
          107,
          68
        ],
        [
          108,
          66
        ],
        [
          110,
          63
        ],
        [
          112,
          61
        ],
        [
          115,
          60
        ],
        [
          116,
          57
        ],
        [
          117,
          56
        ],
        [
          118,
          56
        ],
        [
          119,
          55
        ],
        [
          120,
          53
        ],
        [
          120,
          48
        ],
        [
          119,
          46
        ],
        [
          117,
          44
        ],
        [
          115,
          42
        ],
        [
          112,
          41
        ],
        [
          111,
          37
        ],
        [
          110,
          35
        ],
        [
          106,
          33
        ],
        [
          102,
          32
        ],
        [
          93,
          32
        ],
        [
          90,
          28
        ],
        [
          88,
          28
        ],
        [
          86,
          27
        ],
        [
          85,
          26
        ],
        [
          84,
          23
        ],
        [
          80,
          20
        ],
        [
          78,
          20
        ],
        [
          77,
          19
        ]
      ],
      "group_id": null,
      "shape_type": "polygon",
      "flags": {}
    },
    {
      "label": "brick",
      "points": [
        [
          476,
          58
        ],
        [
          476,
          60
        ],
        [
          476,
          61
        ],
        [
          475,
          65
        ],
        [
          475,
          67
        ],
        [
          473,
          71
        ],
        [
          474,
          73
        ],
        [
          473,
          75
        ],
        [
          474,
          79
        ],
        [
          474,
          80
        ],
        [
          474,
          82
        ],
        [
          472,
          85
        ],
        [
          472,
          87
        ],
        [
          472,
          90
        ],
        [
          473,
          93
        ],
        [
          472,
          95
        ],
        [
          473,
          97
        ],
        [
          471,
          98
        ],
        [
          471,
          104
        ],
        [
          471,
          107
        ],
        [
          473,
          111
        ],
        [
          473,
          114
        ],
        [
          473,
          119
        ],
        [
          471,
          122
        ],
        [
          472,
          124
        ],
        [
          470,
          125
        ],
        [
          468,
          127
        ],
        [
          469,
          131
        ],
        [
          469,
          132
        ],
        [
          469,
          134
        ],
        [
          467,
          137
        ],
        [
          468,
          142
        ],
        [
          465,
          144
        ],
        [
          464,
          146
        ],
        [
          465,
          148
        ],
        [
          465,
          151
        ],
        [
          462,
          150
        ],
        [
          459,
          150
        ],
        [
          454,
          152
        ],
        [
          453,
          155
        ],
        [
          450,
          155
        ],
        [
          446,
          150
        ],
        [
          438,
          154
        ],
        [
          437,
          152
        ],
        [
          436,
          151
        ],
        [
          434,
          148
        ],
        [
          428,
          151
        ],
        [
          428,
          153
        ],
        [
          426,
          150
        ],
        [
          422,
          152
        ],
        [
          415,
          151
        ],
        [
          414,
          149
        ],
        [
          413,
          148
        ],
        [
          405,
          150
        ],
        [
          404,
          148
        ],
        [
          402,
          147
        ],
        [
          394,
          149
        ],
        [
          393,
          147
        ],
        [
          392,
          147
        ],
        [
          390,
          143
        ],
        [
          385,
          145
        ],
        [
          382,
          145
        ],
        [
          380,
          145
        ],
        [
          379,
          143
        ],
        [
          378,
          142
        ],
        [
          376,
          139
        ],
        [
          374,
          138
        ],
        [
          374,
          136
        ],
        [
          372,
          136
        ],
        [
          372,
          134
        ],
        [
          372,
          131
        ],
        [
          371,
          124
        ],
        [
          372,
          113
        ],
        [
          372,
          110
        ],
        [
          373,
          106
        ],
        [
          374,
          101
        ],
        [
          373,
          90
        ],
        [
          373,
          84
        ],
        [
          375,
          81
        ],
        [
          375,
          78
        ],
        [
          374,
          73
        ],
        [
          374,
          70
        ],
        [
          375,
          64
        ],
        [
          376,
          61
        ],
        [
          377,
          53
        ],
        [
          376,
          48
        ],
        [
          378,
          45
        ],
        [
          377,
          43
        ],
        [
          380,
          35
        ],
        [
          382,
          34
        ],
        [
          383,
          33
        ],
        [
          385,
          34
        ],
        [
          388,
          33
        ],
        [
          390,
          33
        ],
        [
          395,
          34
        ],
        [
          399,
          35
        ],
        [
          411,
          35
        ],
        [
          413,
          35
        ],
        [
          418,
          38
        ],
        [
          421,
          37
        ],
        [
          423,
          37
        ],
        [
          428,
          39
        ],
        [
          432,
          40
        ],
        [
          437,
          40
        ],
        [
          441,
          39
        ],
        [
          452,
          40
        ],
        [
          454,
          40
        ],
        [
          455,
          40
        ],
        [
          457,
          42
        ],
        [
          460,
          43
        ],
        [
          466,
          43
        ],
        [
          468,
          44
        ],
        [
          469,
          45
        ],
        [
          470,
          46
        ],
        [
          472,
          47
        ],
        [
          473,
          49
        ]
      ],
      "group_id": null,
      "shape_type": "polygon",
      "flags": {}
    },
    {
      "label": "brick",
      "points": [
        [
          720,
          156
        ],
        [
          725,
          157
        ],
        [
          728,
          158
        ],
        [
          732,
          158
        ],
        [
          740,
          160
        ],
        [
          744,
          159
        ],
        [
          745,
          160
        ],
        [
          747,
          159
        ],
        [
          750,
          157
        ],
        [
          751,
          158
        ],
        [
          753,
          158
        ],
        [
          754,
          157
        ],
        [
          759,
          159
        ],
        [
          760,
          159
        ],
        [
          762,
          160
        ],
        [
          767,
          158
        ],
        [
          768,
          159
        ],
        [
          772,
          157
        ],
        [
          773,
          157
        ],
        [
          778,
          159
        ],
        [
          779,
          158
        ],
        [
          781,
          159
        ],
        [
          783,
          157
        ],
        [
          787,
          158
        ],
        [
          789,
          158
        ],
        [
          790,
          159
        ],
        [
          792,
          158
        ],
        [
          795,
          156
        ],
        [
          797,
          156
        ],
        [
          801,
          155
        ],
        [
          803,
          156
        ],
        [
          805,
          154
        ],
        [
          811,
          155
        ],
        [
          813,
          154
        ],
        [
          815,
          150
        ],
        [
          817,
          149
        ],
        [
          821,
          150
        ],
        [
          822,
          150
        ],
        [
          824,
          151
        ],
        [
          828,
          146
        ],
        [
          832,
          148
        ],
        [
          832,
          145
        ],
        [
          831,
          143
        ],
        [
          832,
          141
        ],
        [
          832,
          137
        ],
        [
          837,
          130
        ],
        [
          841,
          125
        ],
        [
          844,
          122
        ],
        [
          848,
          124
        ],
        [
          845,
          121
        ],
        [
          848,
          115
        ],
        [
          845,
          112
        ],
        [
          845,
          109
        ],
        [
          840,
          104
        ],
        [
          841,
          102
        ],
        [
          841,
          101
        ],
        [
          840,
          99
        ],
        [
          839,
          96
        ],
        [
          842,
          91
        ],
        [
          840,
          90
        ],
        [
          840,
          87
        ],
        [
          840,
          84
        ],
        [
          837,
          81
        ],
        [
          836,
          77
        ],
        [
          835,
          76
        ],
        [
          834,
          75
        ],
        [
          831,
          73
        ],
        [
          831,
          69
        ],
        [
          829,
          68
        ],
        [
          829,
          67
        ],
        [
          823,
          62
        ],
        [
          818,
          59
        ],
        [
          810,
          58
        ],
        [
          796,
          57
        ],
        [
          791,
          55
        ],
        [
          789,
          57
        ],
        [
          788,
          57
        ],
        [
          782,
          57
        ],
        [
          780,
          56
        ],
        [
          778,
          59
        ],
        [
          775,
          59
        ],
        [
          771,
          59
        ],
        [
          770,
          59
        ],
        [
          763,
          59
        ],
        [
          758,
          61
        ],
        [
          754,
          60
        ],
        [
          748,
          62
        ],
        [
          746,
          62
        ],
        [
          744,
          62
        ],
        [
          743,
          62
        ],
        [
          741,
          61
        ],
        [
          740,
          62
        ],
        [
          735,
          64
        ],
        [
          730,
          63
        ],
        [
          726,
          64
        ],
        [
          724,
          63
        ],
        [
          721,
          64
        ],
        [
          718,
          64
        ],
        [
          714,
          65
        ],
        [
          710,
          65
        ],
        [
          704,
          66
        ],
        [
          700,
          67
        ],
        [
          697,
          69
        ],
        [
          695,
          70
        ],
        [
          689,
          78
        ],
        [
          686,
          80
        ],
        [
          683,
          85
        ],
        [
          683,
          87
        ],
        [
          685,
          94
        ],
        [
          684,
          96
        ],
        [
          683,
          98
        ],
        [
          683,
          100
        ],
        [
          685,
          101
        ],
        [
          685,
          103
        ],
        [
          689,
          105
        ],
        [
          692,
          108
        ],
        [
          693,
          109
        ],
        [
          693,
          112
        ],
        [
          695,
          114
        ],
        [
          696,
          120
        ],
        [
          697,
          121
        ],
        [
          700,
          124
        ],
        [
          702,
          125
        ],
        [
          703,
          127
        ],
        [
          705,
          129
        ],
        [
          705,
          134
        ],
        [
          707,
          137
        ],
        [
          708,
          138
        ],
        [
          710,
          144
        ],
        [
          711,
          145
        ],
        [
          712,
          148
        ],
        [
          714,
          150
        ],
        [
          718,
          152
        ]
      ],
      "group_id": null,
      "shape_type": "polygon",
      "flags": {}
    },
    {
      "label": "brick",
      "points": [
        [
          128,
          416
        ],
        [
          129,
          408
        ],
        [
          133,
          395
        ],
        [
          136,
          383
        ],
        [
          136,
          382
        ],
        [
          136,
          380
        ],
        [
          134,
          377
        ],
        [
          135,
          373
        ],
        [
          132,
          375
        ],
        [
          131,
          377
        ],
        [
          129,
          379
        ],
        [
          126,
          378
        ],
        [
          123,
          379
        ],
        [
          116,
          377
        ],
        [
          114,
          374
        ],
        [
          108,
          372
        ],
        [
          105,
          373
        ],
        [
          99,
          371
        ],
        [
          74,
          362
        ],
        [
          72,
          359
        ],
        [
          67,
          357
        ],
        [
          66,
          355
        ],
        [
          66,
          353
        ],
        [
          61,
          350
        ],
        [
          61,
          347
        ],
        [
          59,
          344
        ],
        [
          57,
          342
        ],
        [
          56,
          344
        ],
        [
          55,
          344
        ],
        [
          52,
          350
        ],
        [
          46,
          348
        ],
        [
          44,
          344
        ],
        [
          44,
          346
        ],
        [
          42,
          346
        ],
        [
          39,
          355
        ],
        [
          37,
          356
        ],
        [
          35,
          358
        ],
        [
          34,
          360
        ],
        [
          35,
          362
        ],
        [
          34,
          366
        ],
        [
          31,
          376
        ],
        [
          29,
          387
        ],
        [
          24,
          399
        ],
        [
          21,
          411
        ],
        [
          18,
          422
        ],
        [
          18,
          429
        ],
        [
          18,
          435
        ],
        [
          19,
          437
        ],
        [
          21,
          437
        ],
        [
          23,
          440
        ],
        [
          28,
          443
        ],
        [
          29,
          441
        ],
        [
          33,
          442
        ],
        [
          37,
          443
        ],
        [
          42,
          443
        ],
        [
          50,
          446
        ],
        [
          52,
          445
        ],
        [
          58,
          443
        ],
        [
          66,
          442
        ],
        [
          69,
          442
        ],
        [
          71,
          441
        ],
        [
          74,
          442
        ],
        [
          77,
          442
        ],
        [
          81,
          443
        ],
        [
          83,
          443
        ],
        [
          86,
          441
        ],
        [
          89,
          442
        ],
        [
          93,
          442
        ],
        [
          98,
          440
        ],
        [
          100,
          441
        ],
        [
          102,
          441
        ],
        [
          104,
          440
        ],
        [
          105,
          440
        ],
        [
          107,
          439
        ],
        [
          110,
          437
        ],
        [
          111,
          437
        ],
        [
          112,
          436
        ],
        [
          113,
          436
        ],
        [
          116,
          435
        ],
        [
          117,
          435
        ],
        [
          118,
          433
        ],
        [
          121,
          432
        ],
        [
          123,
          429
        ]
      ],
      "group_id": null,
      "shape_type": "polygon",
      "flags": {}
    }
  ],
  "imagePath": "20220524_17595491.png",
  "imageData": null,
  "imageHeight": 990,
  "imageWidth": 990
}